README.txt
setup.py
Titley.egg-info/PKG-INFO
Titley.egg-info/SOURCES.txt
Titley.egg-info/dependency_links.txt
Titley.egg-info/entry_points.txt
Titley.egg-info/not-zip-safe
Titley.egg-info/requires.txt
Titley.egg-info/top_level.txt
titley/__init__.py
titley/__main__.py
titley/imdb.py
titley/omdb.py
titley/report.py
titley/titley.py
titley/unpacker.py
titley/lib/Bot/__init__.py
titley/lib/Bot/bot.py
titley/lib/UserAgent/__init__.py
titley/lib/UserAgent/tests.py
titley/lib/UserAgent/useragent.py
titley/sources/__init__.py
titley/sources/opensubtitles.py