Metadata-Version: 1.0
Name: Titley
Version: 1.7
Summary: To download and find matching subtitle for a movie.
Home-page: http://bitbucket.org/sras/titley
Author: Sandeep.C.R
Author-email: sandeepcr2@gmail.com
License: MIT
Platform: UNKNOWN
